[
  {"cert_id": "SAP-CYBERESS", "supplier_id": "sap", "supplier_name": "SAP SE", "type": "Cyber Essentials Plus", "issued": "2025-04-16", "expiry": "2026-04-15", "status": "Expired", "days_to_expiry": -26},
  {"cert_id": "ORCL-ISO9001", "supplier_id": "oracle", "supplier_name": "Oracle Corporation", "type": "ISO 9001", "issued": "2022-11-01", "expiry": "2025-11-01", "status": "Expired", "days_to_expiry": -192},
  {"cert_id": "MSFT-ISO9001", "supplier_id": "microsoft", "supplier_name": "Microsoft Corporation", "type": "ISO 9001", "issued": "2023-06-01", "expiry": "2026-05-31", "status": "Expiring Soon", "days_to_expiry": 20},
  {"cert_id": "WDAY-ISO27018", "supplier_id": "workday", "supplier_name": "Workday Inc.", "type": "ISO 27018", "issued": "2023-05-26", "expiry": "2026-05-25", "status": "Expiring Soon", "days_to_expiry": 14},
  {"cert_id": "PEGA-ISO27001", "supplier_id": "pega", "supplier_name": "Pegasystems Inc.", "type": "ISO 27001", "issued": "2023-06-15", "expiry": "2026-06-15", "status": "Expiring Soon", "days_to_expiry": 35},
  {"cert_id": "WDAY-ISO27001", "supplier_id": "workday", "supplier_name": "Workday Inc.", "type": "ISO 27001", "issued": "2023-07-01", "expiry": "2026-06-30", "status": "Expiring Soon", "days_to_expiry": 50},
  {"cert_id": "SAP-ISO27001", "supplier_id": "sap", "supplier_name": "SAP SE", "type": "ISO 27001", "issued": "2023-07-13", "expiry": "2026-07-12", "status": "Expiring Soon", "days_to_expiry": 62},
  {"cert_id": "MSFT-ISO27001", "supplier_id": "microsoft", "supplier_name": "Microsoft Corporation", "type": "ISO 27001", "issued": "2023-08-15", "expiry": "2026-08-14", "status": "Valid", "days_to_expiry": 95},
  {"cert_id": "SFDC-SOCII", "supplier_id": "salesforce", "supplier_name": "Salesforce Inc.", "type": "SOC 2 Type II", "issued": "2024-08-02", "expiry": "2026-08-01", "status": "Valid", "days_to_expiry": 82},
  {"cert_id": "ATLS-SOCII", "supplier_id": "atlassian", "supplier_name": "Atlassian Corporation", "type": "SOC 2 Type II", "issued": "2024-09-01", "expiry": "2026-08-31", "status": "Valid", "days_to_expiry": 112}
]
